versus_cli/__init__.py
versus_cli/__main__.py
versus_cli-0.2.1.dist-info/METADATA
versus_cli-0.2.1.dist-info/WHEEL
versus_cli-0.2.1.dist-info/entry_points.txt
versus_cli-0.2.1.dist-info/RECORD
