Metadata-Version: 2.1
Name: versus-cli
Version: 0.2.1
Summary: Run A vs. B analyses, storing analysis input, command and result in YAMLized dataframe. Part of Wistan infrastructure.
Author: Ben Skubi
Author-email: bskubi@gmail.com
Requires-Python: >=3.12,<4.0
Classifier: Programming Language :: Python :: 3
Classifier: Programming Language :: Python :: 3.12
